eremiza/__init__.py
eremiza/_alarm.py
eremiza/_client.py
eremiza/_utils.py
eremiza_api-0.2.0.dist-info/LICENSE
eremiza_api-0.2.0.dist-info/METADATA
eremiza_api-0.2.0.dist-info/WHEEL
eremiza_api-0.2.0.dist-info/top_level.txt
eremiza_api-0.2.0.dist-info/RECORD
