Metadata-Version: 2.1
Name: eremiza-api
Version: 0.2.0
Summary: UNKNOWN
Home-page: UNKNOWN
Author: Kacper Ziubryniewicz
Author-email: kapi2289@gmail.com
License: MIT
Platform: UNKNOWN
Requires-Dist: requests
Requires-Dist: PyJWT
Requires-Dist: related
Requires-Dist: aenum
